{
  "id": "episode_45",
  "season": 2,
  "episode": 30,
  "title": "THE PRICE",
  "startNodeId": "e45_n01",

  "flagsUsed": [
    "sendEva",
    "sendMara"
  ],

  "persistentVariables": {
    "openedInnerLayer": false,
    "observerPower": 0,
    "aeonStability": 100,
    "noahTrust": 50
  },

  "nodes": {
    "e45_n01": {
      "id": "e45_n01",
      "speaker": "SYSTEM",
      "events": [
        {
          "type": "conditionalBranch",
          "condition": "sendEva == true",
          "targetNodeId": "eva_branch_01"
        },
        {
          "type": "conditionalBranch",
          "condition": "sendMara == true",
          "targetNodeId": "mara_branch_01"
        }
      ]
    },

    "eva_branch_01": {
      "id": "eva_branch_01",
      "speaker": "EVA",
      "events": [
        {
          "type": "message",
          "text": "I'm okay."
        },
        {
          "type": "message",
          "text": "Mostly."
        }
      ],
      "choices": [
        {
          "id": "continue_eva_01",
          "text": "CONTINUE.",
          "nextNodeId": "eva_branch_02"
        }
      ]
    },

    "eva_branch_02": {
      "id": "eva_branch_02",
      "speaker": "EVA",
      "events": [
        {
          "type": "message",
          "text": "Okay, that's a lie."
        },
        {
          "type": "message",
          "text": "It hurts."
        }
      ],
      "choices": [
        {
          "id": "continue_eva_02",
          "text": "CONTINUE.",
          "nextNodeId": "eva_branch_03"
        }
      ]
    },

    "eva_branch_03": {
      "id": "eva_branch_03",
      "speaker": "GRANT",
      "events": [
        {
          "type": "message",
          "text": "Define hurts."
        }
      ],
      "choices": [
        {
          "id": "continue_eva_03",
          "text": "CONTINUE.",
          "nextNodeId": "eva_branch_04"
        }
      ]
    },

    "eva_branch_04": {
      "id": "eva_branch_04",
      "speaker": "EVA",
      "events": [
        {
          "type": "message",
          "text": "The kind where I pretend I'm fine and everyone politely doesn't believe me."
        }
      ],
      "choices": [
        {
          "id": "continue_eva_04",
          "text": "CONTINUE.",
          "nextNodeId": "eva_branch_05"
        }
      ]
    },

    "eva_branch_05": {
      "id": "eva_branch_05",
      "speaker": "NOAH",
      "events": [
        {
          "type": "message",
          "text": "Eva..."
        }
      ],
      "choices": [
        {
          "id": "continue_eva_05",
          "text": "CONTINUE.",
          "nextNodeId": "eva_branch_06"
        }
      ]
    },

    "eva_branch_06": {
      "id": "eva_branch_06",
      "speaker": "EVA",
      "events": [
        {
          "type": "message",
          "text": "Don't."
        },
        {
          "type": "message",
          "text": "We got the file, right?"
        }
      ],
      "choices": [
        {
          "id": "continue_eva_06",
          "text": "CONTINUE.",
          "nextNodeId": "eva_branch_07"
        }
      ]
    },

    "eva_branch_07": {
      "id": "eva_branch_07",
      "speaker": "SYSTEM",
      "events": [
        {
          "type": "file",
          "fileId": "evelyn_final_fragment",
          "title": "EVELYN FINAL FRAGMENT",
          "content": "EVELYN CARTER\n\nTRANSFER STATUS: PARTIAL\n\nCONSCIOUSNESS ANCHOR: ACTIVE\n\nLOCATION: AEON INNER LAYER"
        }
      ],
      "choices": [
        {
          "id": "merge_branch_01",
          "text": "CONTINUE.",
          "nextNodeId": "shared_reveal_01"
        }
      ]
    },

    "mara_branch_01": {
      "id": "mara_branch_01",
      "speaker": "MARA",
      "events": [
        {
          "type": "message",
          "text": "The archive was empty."
        }
      ],
      "choices": [
        {
          "id": "continue_mara_01",
          "text": "CONTINUE.",
          "nextNodeId": "mara_branch_02"
        }
      ]
    },

    "mara_branch_02": {
      "id": "mara_branch_02",
      "speaker": "EVA",
      "events": [
        {
          "type": "message",
          "text": "Empty how?"
        }
      ],
      "choices": [
        {
          "id": "continue_mara_02",
          "text": "CONTINUE.",
          "nextNodeId": "mara_branch_03"
        }
      ]
    },

    "mara_branch_03": {
      "id": "mara_branch_03",
      "speaker": "MARA",
      "events": [
        {
          "type": "message",
          "text": "Not deleted."
        },
        {
          "type": "message",
          "text": "Taken."
        }
      ],
      "choices": [
        {
          "id": "continue_mara_03",
          "text": "CONTINUE.",
          "nextNodeId": "mara_branch_04"
        }
      ]
    },

    "mara_branch_04": {
      "id": "mara_branch_04",
      "speaker": "GRANT",
      "events": [
        {
          "type": "message",
          "text": "I hate when files get dramatic."
        }
      ],
      "choices": [
        {
          "id": "continue_mara_04",
          "text": "CONTINUE.",
          "nextNodeId": "mara_branch_05"
        }
      ]
    },

    "mara_branch_05": {
      "id": "mara_branch_05",
      "speaker": "MARA",
      "events": [
        {
          "type": "message",
          "text": "Grant."
        }
      ],
      "choices": [
        {
          "id": "continue_mara_05",
          "text": "CONTINUE.",
          "nextNodeId": "mara_branch_06"
        }
      ]
    },

    "mara_branch_06": {
      "id": "mara_branch_06",
      "speaker": "GRANT",
      "events": [
        {
          "type": "message",
          "text": "Sorry. Coping mechanism."
        }
      ],
      "choices": [
        {
          "id": "continue_mara_06",
          "text": "CONTINUE.",
          "nextNodeId": "mara_branch_07"
        }
      ]
    },

    "mara_branch_07": {
      "id": "mara_branch_07",
      "speaker": "SYSTEM",
      "events": [
        {
          "type": "file",
          "fileId": "archive_loss_report",
          "title": "ARCHIVE LOSS REPORT",
          "content": "EVELYN RECORDS: REMOVED\n\nLAST ACCESS: OBSERVER"
        }
      ],
      "choices": [
        {
          "id": "merge_branch_02",
          "text": "CONTINUE.",
          "nextNodeId": "shared_reveal_01"
        }
      ]
    },

    "shared_reveal_01": {
      "id": "shared_reveal_01",
      "speaker": "OBSERVER",
      "events": [
        {
          "type": "message",
          "text": "Evelyn is not dead."
        }
      ],
      "choices": [
        {
          "id": "continue_shared_01",
          "text": "CONTINUE.",
          "nextNodeId": "shared_reveal_02"
        }
      ]
    },

    "shared_reveal_02": {
      "id": "shared_reveal_02",
      "speaker": "OBSERVER",
      "events": [
        {
          "type": "message",
          "text": "But she is not free."
        }
      ],
      "choices": [
        {
          "id": "continue_shared_02",
          "text": "CONTINUE.",
          "nextNodeId": "shared_reveal_03"
        }
      ]
    },

    "shared_reveal_03": {
      "id": "shared_reveal_03",
      "speaker": "NOAH",
      "events": [
        {
          "type": "message",
          "text": "Where is she?"
        }
      ],
      "choices": [
        {
          "id": "continue_shared_03",
          "text": "CONTINUE.",
          "nextNodeId": "shared_reveal_04"
        }
      ]
    },

    "shared_reveal_04": {
      "id": "shared_reveal_04",
      "speaker": "OBSERVER",
      "events": [
        {
          "type": "message",
          "text": "Inside the layer you were never meant to open."
        }
      ],
      "choices": [
        {
          "id": "continue_shared_04",
          "text": "CONTINUE.",
          "nextNodeId": "shared_reveal_05"
        }
      ]
    },

    "shared_reveal_05": {
      "id": "shared_reveal_05",
      "speaker": "SYSTEM",
      "events": [
        {
          "type": "systemAlert",
          "text": "[INNER LAYER ACCESS DETECTED]"
        }
      ],
      "choices": [
        {
          "id": "inner_layer_choice",
          "text": "CONTINUE.",
          "nextNodeId": "inner_layer_decision"
        }
      ]
    },

    "inner_layer_decision": {
      "id": "inner_layer_decision",
      "speaker": "SYSTEM",
      "events": [
        {
          "type": "decision",
          "text": "Open the Inner Layer?"
        }
      ],
      "choices": [
        {
          "id": "open_inner_layer",
          "text": "OPEN INNER LAYER",
          "effects": {
            "openedInnerLayer": true,
            "observerPower": 15,
            "aeonStability": -20
          },
          "nextNodeId": "open_path_01"
        },
        {
          "id": "seal_inner_layer",
          "text": "SEAL IT FOR NOW",
          "effects": {
            "openedInnerLayer": false,
            "noahTrust": -15,
            "aeonStability": 10
          },
          "nextNodeId": "seal_path_01"
        }
      ]
    },

    "open_path_01": {
      "id": "open_path_01",
      "speaker": "SYSTEM",
      "events": [
        {
          "type": "systemAlert",
          "text": "[INNER LAYER OPENING]"
        },
        {
          "type": "glitch",
          "duration": 12000
        }
      ],
      "choices": [
        {
          "id": "continue_open_01",
          "text": "CONTINUE.",
          "nextNodeId": "open_path_02"
        }
      ]
    },

    "open_path_02": {
      "id": "open_path_02",
      "speaker": "EVELYN",
      "events": [
        {
          "type": "message",
          "text": "Noah?"
        }
      ],
      "choices": [
        {
          "id": "season_end_open",
          "text": "END SEASON",
          "nextSeasonId": "season_3"
        }
      ]
    },

    "seal_path_01": {
      "id": "seal_path_01",
      "speaker": "SYSTEM",
      "events": [
        {
          "type": "systemAlert",
          "text": "[INNER LAYER SEALED]"
        }
      ],
      "choices": [
        {
          "id": "continue_seal_01",
          "text": "CONTINUE.",
          "nextNodeId": "seal_path_02"
        }
      ]
    },

    "seal_path_02": {
      "id": "seal_path_02",
      "speaker": "NOAH",
      "events": [
        {
          "type": "message",
          "text": "You had a chance."
        },
        {
          "type": "message",
          "text": "And you stopped it."
        }
      ],
      "choices": [
        {
          "id": "continue_seal_02",
          "text": "CONTINUE.",
          "nextNodeId": "seal_path_03"
        }
      ]
    },

    "seal_path_03": {
      "id": "seal_path_03",
      "speaker": "SYSTEM",
      "events": [
        {
          "type": "backgroundSignal",
          "text": "Weak signal detected."
        }
      ],
      "choices": [
        {
          "id": "continue_seal_03",
          "text": "CONTINUE.",
          "nextNodeId": "seal_path_04"
        }
      ]
    },

    "seal_path_04": {
      "id": "seal_path_04",
      "speaker": "EVELYN",
      "events": [
        {
          "type": "message",
          "text": "Noah?"
        }
      ],
      "choices": [
        {
          "id": "continue_seal_04",
          "text": "CONTINUE.",
          "nextNodeId": "seal_path_05"
        }
      ]
    },

    "seal_path_05": {
      "id": "seal_path_05",
      "speaker": "SYSTEM",
      "events": [
        {
          "type": "signalLost",
          "text": "[SIGNAL LOST]"
        }
      ],
      "choices": [
        {
          "id": "season_end_seal",
          "text": "END SEASON",
          "nextSeasonId": "season_3"
        }
      ]
    }
  }
}